LICENSE.txt
MANIFEST.in
README.rst
importhandler.py
predictor.py
requirements.txt
setup.py
trainer.py
transformer.py
cloudml/__init__.py
cloudml/jsonpath.py
cloudml/utils.py
cloudml.egg-info/PKG-INFO
cloudml.egg-info/SOURCES.txt
cloudml.egg-info/dependency_links.txt
cloudml.egg-info/requires.txt
cloudml.egg-info/top_level.txt
cloudml/importhandler/__init__.py
cloudml/importhandler/base.py
cloudml/importhandler/datasources.py
cloudml/importhandler/db.py
cloudml/importhandler/entities.py
cloudml/importhandler/exceptions.py
cloudml/importhandler/importhandler.py
cloudml/importhandler/inputs.py
cloudml/importhandler/predict.py
cloudml/importhandler/processors.py
cloudml/importhandler/schema.xsd
cloudml/importhandler/scripts.py
cloudml/importhandler/utils.py
cloudml/importhandler/templates/pig_template.txt
cloudml/importhandler/tests/__init__.py
cloudml/importhandler/tests/constants.py
cloudml/importhandler/tests/datasource_tests.py
cloudml/importhandler/tests/entity_tests.py
cloudml/importhandler/tests/field_tests.py
cloudml/importhandler/tests/importhandler_tests.py
cloudml/importhandler/tests/input_tests.py
cloudml/importhandler/tests/predict_tests.py
cloudml/importhandler/tests/processor_tests.py
cloudml/importhandler/tests/script_tests.py
cloudml/importhandler/tests/sqoop_tests.py
cloudml/importhandler/tests/utils_tests.py
cloudml/tests/__init__.py
cloudml/tests/importhandler_tests.py
cloudml/tests/predictor_tests.py
cloudml/tests/test_utils.py
cloudml/tests/trainer_tests.py
cloudml/tests/transformer_tests.py
cloudml/trainer/__init__.py
cloudml/trainer/classifier_settings.py
cloudml/trainer/config.py
cloudml/trainer/exceptions.py
cloudml/trainer/metrics.py
cloudml/trainer/scalers.py
cloudml/trainer/store.py
cloudml/trainer/streamutils.py
cloudml/trainer/trainer.py
cloudml/trainer/transformers.py
cloudml/trainer/utils.py
cloudml/trainer/feature_types/__init__.py
cloudml/trainer/feature_types/base.py
cloudml/trainer/feature_types/categorical.py
cloudml/trainer/feature_types/composite.py
cloudml/trainer/feature_types/date.py
cloudml/trainer/feature_types/ordinal.py
cloudml/trainer/feature_types/primitive_types.py
