Metadata-Version: 1.1
Name: cloudml
Version: 0.4.2
Summary: Machine learning as a service scipy-trainer
Home-page: http://www.upwork.com
Author: Nikolay Melnik
Author-email: nmelnik@cloud.upwork.com
License: UNKNOWN
Platform: UNKNOWN
Classifier: Environment :: Console
Classifier: Intended Audience :: Information Technology
Classifier: Operating System :: OS Independent
Classifier: Programming Language :: Python
Classifier: Programming Language :: Python :: 2.7
